<?xml version="1.0" encoding="utf-8" ?>
<Items title="nihao">
<item text="邓紫棋开讲 "      des="">
    <title>环球音乐</title>
    <content>环球音乐</content>
    <text> 
    </text>
    <filepath>http://ent.huanqiu.com/</filepath>
    <date>2015/03/22</date>
    <from>tx</from>
    <url>http://ent.qq.com/a/20150313/053673.htm</url>
    <picurl>http://img1.gtimg.com/ent/pics/hv1/14/63/1803/117256154.png</picurl>
  </item>
  <item text="邓紫棋开讲 "      des="">
    <title>网易音乐</title>
    <content>网易音乐</content>
    <text> 
    </text>
    <filepath>http://ent.163.com/music/</filepath>
    <date>2015/03/22</date>
    <from>tx</from>
    <url>http://ent.qq.com/a/20150313/053673.htm</url>
    <picurl>http://img1.gtimg.com/ent/pics/hv1/14/63/1803/117256154.png</picurl>
  </item>
  <item text="邓紫棋开讲 "      des="">
    <title>实体唱片被取代是必然趋势</title>
    <content>音乐产业和其它类型产业一样都要与时俱进。在新的媒介诞生并迅猛发展的今天，音乐产业应该思考如何更好地依附新媒介，而不是如何对抗。但想要吃好新媒介这块蛋糕并不是件容易的事。</content>
    <text>     
      笔者采访后发现，九成以上的业内人士都认为实体唱片被取代是必然趋势，音乐产业和其它类型产业一样都要与时俱进。在新的媒介诞生并迅猛发展的今天，音乐产业应该思考如何更好地依附新媒介，而不是如何对抗。但想要吃好新媒介这块蛋糕并不是件容易的事。俗话说“无利不起早”，没有收益，任何产业都要完蛋。“想听音乐又不想花钱”和“想让鸡下蛋却不给鸡吃饭”是一个道理。为此我们首先要改变“不劳而获”的意识，不论是实体唱片还是数字唱片，一首好歌是无数人辛勤劳动的产物，我们理应为此付出金钱。同时，国家应完善知识产权保护体系并加强监管。这样留给音乐人和唱片公司的只剩下“最后的考验”了
    </text>
    <filepath>http://gisdaodao.github.io/itsites/news1.html</filepath>
    <date>2015/03/22</date>
    <from>tx</from>
    <url>http://ent.qq.com/a/20150313/053673.htm</url>
    <picurl>http://img1.gtimg.com/ent/pics/hv1/14/63/1803/117256154.png</picurl>
  </item>
 <item text="邓紫棋开讲 "      des="">
    <title>视频: 彼岸 汪峰 翻唱</title>
    <content>视频: 彼岸 汪峰 翻唱</content>
    <text> 
    </text>
    <filepath>http://v.youku.com/v_show/id_XOTIwNDA3MjYw.html?qq-pf-to=pcqq.group</filepath>
    <date>2015/03/22</date>
    <from>tx</from>
    <url>http://ent.qq.com/a/20150313/053673.htm</url>
    <picurl>http://img1.gtimg.com/ent/pics/hv1/14/63/1803/117256154.png</picurl>
  </item>
<item text="邓紫棋开讲 "      des="">
    <title>孙楠《我是歌手3》退赛：音乐不够戏剧凑</title>
    <content>孙楠《我是歌手3》退赛：音乐不够戏剧凑</content>
    <text> 
    </text>
    <filepath>http://ent.163.com/15/0401/10/AM40A8S700032DGD.html</filepath>
    <date>2015/03/22</date>
    <from>tx</from>
    <url>http://ent.qq.com/a/20150313/053673.htm</url>
    <picurl>http://img1.gtimg.com/ent/pics/hv1/14/63/1803/117256154.png</picurl>
  </item>
<item text="邓紫棋开讲 "      des="">
    <title>欧美一周：像“大白”一样治愈的歌手们</title>
    <content>拥有一个“大白”是当下现代人最急切的愿望。这个因《超能陆战队》而晋升全民宠儿的蠢萌机器人，成为继机器猫后又一位全能治愈系卡通人物。</content>
    <text> 
    </text>
    <filepath>http://ent.163.com/15/0323/10/ALCR9JLR00031H0O.html</filepath>
    <date>2015/03/22</date>
    <from>tx</from>
    <url>http://ent.qq.com/a/20150313/053673.htm</url>
    <picurl>http://img1.gtimg.com/ent/pics/hv1/14/63/1803/117256154.png</picurl>
  </item>
<item text="邓紫棋开讲 "      des="">
    <title>欧美一周：“蹲妹”卡莉一辈子只会唱一首歌</title>
    <content>2012年夏天，全世界都被卡莉·蕾·吉普森《Call Me Maybe》洗脑，而副作用是，这辈子职业生涯都被规划在《Call Me Maybe》的阴影之下。</content>
    <text> 
    </text>
    <filepath>http://ent.163.com/15/0316/10/AKQQFCOO00031H0O.html</filepath>
    <date>2015/03/22</date>
    <from>tx</from>
    <url>http://ent.qq.com/a/20150313/053673.htm</url>
    <picurl>http://img1.gtimg.com/ent/pics/hv1/14/63/1803/117256154.png</picurl>
  </item>
<item text="邓紫棋开讲 "      des="">
    <title>音乐周</title>
    <content>音乐周</content>
    <text> 
    </text>
    <filepath>http://www.musicweek.com/</filepath>
    <date>2015/03/22</date>
    <from>tx</from>
    <url>http://ent.qq.com/a/20150313/053673.htm</url>
    <picurl>http://img1.gtimg.com/ent/pics/hv1/14/63/1803/117256154.png</picurl>
  </item>
<item text="邓紫棋开讲 "      des="">
    <title>微行音乐资讯</title>
    <content>微行音乐资讯</content>
    <text> 
    </text>
    <filepath>http://ent.qq.com/music/music_inc/music_yjcx.htm</filepath>
    <date>2015/03/22</date>
    <from>tx</from>
    <url>http://ent.qq.com/a/20150313/053673.htm</url>
    <picurl>http://img1.gtimg.com/ent/pics/hv1/14/63/1803/117256154.png</picurl>
  </item>
<item text="邓紫棋开讲 "      des="">
    <title>视频: 【孙小黑】02汪峰-北京北京翻唱</title>
    <content>视频: 【孙小黑】02汪峰-北京北京翻唱</content>
    <text> 
    </text>
    <filepath>http://v.youku.com/v_show/id_XOTMwNTA4ODUy.html</filepath>
    <date>2015/03/22</date>
    <from>tx</from>
    <url>http://ent.qq.com/a/20150313/053673.htm</url>
    <picurl>http://img1.gtimg.com/ent/pics/hv1/14/63/1803/117256154.png</picurl>
  </item>
<item text="邓紫棋开讲 "      des="">
    <title>视频: 【孙小黑】01许巍-礼物翻唱</title>
    <content>视频: 【孙小黑】01许巍-礼物翻唱</content>
    <text> 
    </text>
    <filepath>http://v.youku.com/v_show/id_XOTMwNTAzNzQ0.html</filepath>
    <date>2015/03/22</date>
    <from>tx</from>
    <url>http://ent.qq.com/a/20150313/053673.htm</url>
    <picurl>http://img1.gtimg.com/ent/pics/hv1/14/63/1803/117256154.png</picurl>
  </item>
<item text="邓紫棋开讲 "      des="">
    <title>微行音乐工作室，大家快来分享吧</title>
    <content>微行音乐工作室，大家快来分享吧</content>
    <text> 
    </text>
    <filepath>http://i.youku.com/u/UMzAxNTU4ODQzNg==</filepath>
    <date>2015/03/22</date>
    <from>tx</from>
    <url>http://ent.qq.com/a/20150313/053673.htm</url>
    <picurl>http://img1.gtimg.com/ent/pics/hv1/14/63/1803/117256154.png</picurl>
  </item>
<item text="邓紫棋开讲 "      des="">
    <title>视频: 彼岸 汪峰 翻唱</title>
    <content>视频: 彼岸 汪峰 翻唱</content>
    <text> 
    </text>
    <filepath>http://v.youku.com/v_show/id_XOTIwNDA3MjYw.html?qq-pf-to=pcqq.group</filepath>
    <date>2015/03/22</date>
    <from>tx</from>
    <url>http://ent.qq.com/a/20150313/053673.htm</url>
    <picurl>http://img1.gtimg.com/ent/pics/hv1/14/63/1803/117256154.png</picurl>
  </item>
</Items>
