<?xml version="1.0" encoding="utf-8" ?>
<Items>
<item text="hao123"      des="">
    <url>http://m.hao123.com/</url>
  </item>
<item text="中国青年网"      des="">
    <url>http://m.youth.cn/</url>
  </item>
 <item text="知音"      des="">
    <url>http://wap.zhiyin.cn/</url>
  </item>
<item text="大公报"      des="">
    <url>http://wap.takungpao.com/</url>
  </item>
<item text="南方周末"      des="">
    <url>http://wap.infzm.com/</url>
  </item>
  <item text="cnbeta"      des="">
    <url>http://m.cnbeta.com/</url>
  </item>
<item text="36kr"      des="">
    <url>http://m.36kr.com/</url>
  </item>
<item text="众筹网"      des="">
    <url>http://m.zhongchou.cn/</url>
  </item>
 <item text="读者"      des="">
    <url>http://wap.hdz8.cn/</url>
  </item>
<item text="学习啦"      des="">
    <url>http://m.xuexila.com/</url>
  </item>
 <item text="听新闻"      des="">
    <url>http://www.52rkl.cn/tingxinwen/</url>
  </item>
 <item text="随便听歌"      des="">
    <url>http://fm.baidu.com/</url>
  </item>
 <item text="荔枝fm"      des="">
    <url>http://www.lizhi.fm/#/promo/1</url>
  </item>
<item text="百度图说天下"      des="">
    <url>http://image.baidu.com/channel/info</url>
  </item>
<item text="MBA智库商学院"      des="">
    <url>http://wiki.mbalib.com/wiki/%E9%A6%96%E9%A1%B5</url>
  </item>
<item text="爱奇艺教育"      des="">
    <url>http://edu.iqiyi.com/</url>
  </item>
<item text="cnet"      des="">
    <url>http://www.cnet.com/videos/</url>
  </item>
<item text="engadget中国"      des="">
    <url>http://cn.engadget.com/</url>
  </item>
<item text="engadget中国"      des="">
    <url>http://cn.engadget.com/</url>
  </item>
<item text="engadget"      des="">
    <url>http://www.engadget.com/</url>
  </item>
  <item text="3G泡泡"      des="">
    <url>http://3gpp.com.cn </url>
  </item>
  <item text="空中网"      des="">
    <url>http://kong.net/</url>
  </item>
  <item text="wap天天图"      des="">
    <url>http://www.waptt.com/</url>
  </item>
<item text="华夏时报"      des="">
    <url>http://www.chinatimes.cc/</url>
  </item>
<item text="开源中国"      des="">
    <url>http://m.oschina.net/</url>
  </item>
<item text="csdn"      des="">
    <url>http://m.csdn.net/</url>
  </item>
<item text="果壳"      des="">
    <url>http://m.guokr.com/</url>
  </item>
<item text="dospy"      des="">
    <url>http://bbs.dospy.com/?forceMobile=1</url>
  </item>
<item text="煎蛋"      des="">
    <url>http://jandan.net/</url>
  </item>
<item text="澎湃新闻网"      des="">
    <url>http://www.thepaper.cn/</url>
  </item>
<item text="香港文汇网"      des="">
    <url>http://m.wenweipo.com/</url>
  </item>
<item text="译言精选"      des="">
    <url>http://m.wenweipo.com/</url>
  </item>
<item text="联合早报网"      des="">
    <url>http://m.zaobao.com/</url>
  </item>
<item text="中国时报网(台湾)"      des="">
    <url>http://www.chinatimes.com/</url>
  </item>
<item text="朝鲜日报"      des="">
    <url>http://www.chosunonline.com/index.html</url>
  </item>
<item text="中华人民共和国中央人民政府门户网站"      des="">
    <url>http://www.gov.cn/</url>
  </item>
<item text="参考消息"      des="">
    <url>http://m.cankaoxiaoxi.com/</url>
  </item>
<item text="cia"      des="">
    <url>https://www.cia.gov/index.html</url>
  </item>
<item text="esa(欧洲航天局)"      des="">
    <url>http://www.esa.int/ESA</url>
  </item>
<item text="美国政府网"      des="">
    <url>http://www.usa.gov/</url>
  </item>
<item text="英国"      des="">
    <url>https://www.gov.uk/</url>
  </item>
<item text="who"      des="">
    <url>http://www.who.int/</url>
  </item>
<item text="中华人民共和国国家卫生和计划生育委员会"      des="">
    <url>http://www.nhfpc.gov.cn/</url>
  </item>
<item text="联合国"      des="">
    <url>http://www.un.org/zh/</url>
  </item>
</Items>

