<?xml version="1.0" encoding="utf-8" ?>
<Items title="nihao">
  <item text="邓紫棋开讲 "      des="">
    <title>烛光里的妈妈</title>
    <content></content>
    <text>       </text>
    <filepath>https://github.com/gisdaodao/itsites/blob/gh-pages/musicfile/%E7%83%9B%E5%85%89%E9%87%8C%E7%9A%84%E5%A6%88%E5%A6%88%20by%E9%9B%84%E7%87%95.mp3</filepath>
    <date>2015/03/22</date>
    <from>雄燕</from>
    <url>http://ent.qq.com/a/20150313/053673.htm</url>
    <picurl>http://img1.gtimg.com/ent/pics/hv1/14/63/1803/117256154.png</picurl>
  </item>
<item text="邓紫棋开讲 "      des="">
    <title>边走边爱</title>
    <content></content>
    <text></text>
    <filepath>https://github.com/gisdaodao/itsites/blob/gh-pages/musicfile/%E8%BE%B9%E8%B5%B0%E8%BE%B9%E7%88%B1%20by%E9%9B%84%E7%87%95.mp3</filepath>
    <date>2015/03/22</date>
    <from>雄燕</from>
    <url>http://ent.qq.com/a/20150313/053673.htm</url>
    <picurl>http://img1.gtimg.com/ent/pics/hv1/14/63/1803/117256154.png</picurl>
  </item>
</Items>
